[{"R1":"192","G1":"231","B1":"215","R2":"82","G2":"217","B2":"165","R3":"111","G3":"168","B3":"142","R4":"21","G4":"28","B4":"24"},{"R1":"213","G1":"191","B1":"239","R2":"135","G2":"100","B2":"179","R3":"138","G3":"59","B3":"236","R4":"19","G4":"17","B4":"24"},{"R1":"191","G1":"227","B1":"239","R2":"100","G2":"160","B2":"179","R3":"59","G3":"192","B3":"236","R4":"17","G4":"23","B4":"24"},{"R1":"239","G1":"191","B1":"199","R2":"179","G2":"100","B2":"115","R3":"236","G3":"59","B3":"91","R4":"24","G4":"17","B4":"19"},{"R1":"255","G1":"218","B1":"168","R2":"255","G2":"170","B2":"44","R3":"255","G3":"146","B3":"24","R4":"49","G4":"20","B4":"0"},{"R1":"230","G1":"230","B1":"230","R2":"151","G2":"151","B2":"151","R3":"138","G3":"138","B3":"138","R4":"7","G4":"7","B4":"7"}]